rsoniUtils/__init__.py
rsoniUtils/Utils/__init__.py
rsoniUtils/Utils/converrt.py
rsoniUtils/Utils/datetimeext.py
rsoniUtils/Utils/datetimeext2.py
rsoniUtils/Utils/foldercontrol.py
rsoniUtils/Utils/stringbuilder.py
rsoniUtils/loggingext/__init__.py
rsoniUtils/loggingext/errorext.py
rsoniUtils/loggingext/logging_helper.py
rsoniUtils/tests/__init__.py
rsoniUtils/tests/testdatetimeext.py
rsoniUtils/ztests/__init__.py
rsoniUtils/ztests/testdatetimeext.py
rsoniUtils-22.10.23.2.data/scripts/data.json
rsoniUtils-22.10.23.2.dist-info/LICENSE
rsoniUtils-22.10.23.2.dist-info/METADATA
rsoniUtils-22.10.23.2.dist-info/WHEEL
rsoniUtils-22.10.23.2.dist-info/top_level.txt
rsoniUtils-22.10.23.2.dist-info/RECORD
