Metadata-Version: 2.1
Name: rsoniUtils
Version: 22.10.23.2
Summary: Utilites used for python
Home-page: 
Author: Rajesh Soni
Author-email: rajesh2511@outlook.com
License: MIT
Keywords: rsoni,utils
Classifier: License :: OSI Approved :: MIT License
Classifier: Programming Language :: Python :: 3
Classifier: Programming Language :: Python :: 3.8
License-File: LICENSE
Requires-Dist: opencensus.ext.azure
